colav_proto/__about__.py
colav_proto/__init__.py
colav_proto/_internal/__init__.py
colav_proto/_internal/proto_type_class_map.py
colav_proto/_internal/proto_type_enums.py
colav_proto/_internal/proto_unwrapper.py
colav_proto/_internal/proto_wrapper.py
colav_proto/constants/__init__.py
colav_proto/constants/_automaton_status_enum.py
colav_proto/constants/_colreg_classification_enum.py
colav_proto/constants/_control_mode_enum.py
colav_proto/constants/_cri_classification_enum.py
colav_proto/constants/_mission_complete_status_enum.py
colav_proto/constants/_proto_types.py
colav_proto/deserialization/__init__.py
colav_proto/deserialization/deserializer.py
colav_proto/generated/python/__init__.py
colav_proto/generated/python/colav/__init__.py
colav_proto/generated/python/colav/colav_wrapper_message_pb2.py
colav_proto/generated/python/colav/automaton/__init__.py
colav_proto/generated/python/colav/automaton/automaton_mission_output_pb2.py
colav_proto/generated/python/colav/automaton/constants/__init__.py
colav_proto/generated/python/colav/automaton/constants/automaton_status_enum_pb2.py
colav_proto/generated/python/colav/automaton/constants/control_mode_enum_pb2.py
colav_proto/generated/python/colav/automaton/constants/mission_status_enum_pb2.py
colav_proto/generated/python/colav/automaton/constants/classifications/__init__.py
colav_proto/generated/python/colav/automaton/constants/classifications/colreg_classification_enum_pb2.py
colav_proto/generated/python/colav/automaton/constants/classifications/cri_classification_enum_pb2.py
colav_proto/generated/python/colav/automaton/dynamics/__init__.py
colav_proto/generated/python/colav/automaton/dynamics/dynamics_pb2.py
colav_proto/generated/python/colav/automaton/states/__init__.py
colav_proto/generated/python/colav/automaton/states/agent_state_pb2.py
colav_proto/generated/python/colav/automaton/states/dynamic_obstacle_risk_state_pb2.py
colav_proto/generated/python/colav/automaton/states/dynamic_obstacle_state_pb2.py
colav_proto-0.0.4.dist-info/METADATA
colav_proto-0.0.4.dist-info/WHEEL
colav_proto-0.0.4.dist-info/licenses/LICENSE.txt
colav_proto-0.0.4.dist-info/RECORD
