Metadata-Version: 2.4
Name: colav-proto
Version: 0.0.4
Summary: A package for generation, serialization and deserialization of colav protobuf messages.
Project-URL: Documentation, https://github.com/Ryan/colav-proto#readme
Project-URL: Issues, https://github.com/Ryan/colav-proto/issues
Project-URL: Source, https://github.com/Ryan/colav-proto
Author-email: Ryan <r.mckee@qub.ac.uk>
License-Expression: MIT
License-File: LICENSE.txt
Classifier: Development Status :: 4 - Beta
Classifier: Programming Language :: Python
Classifier: Programming Language :: Python :: 3.8
Classifier: Programming Language :: Python :: 3.9
Classifier: Programming Language :: Python :: 3.10
Classifier: Programming Language :: Python :: 3.11
Classifier: Programming Language :: Python :: 3.12
Classifier: Programming Language :: Python :: Implementation :: CPython
Classifier: Programming Language :: Python :: Implementation :: PyPy
Requires-Python: >=3.8
Requires-Dist: hatch
Requires-Dist: lark
Requires-Dist: numpy
Requires-Dist: protobuf
Requires-Dist: pytest
Requires-Dist: pyyaml
Requires-Dist: shapely
